examples/__init__.py
examples/simple_http_check.py
examples/test_script.py
examples/test_table_for_measurements.py
examples/test_table_for_permutations.py
examples/xunit_suite.py
questions_three/__init__.py
questions_three/module_cfg.yml
questions_three/ci/__init__.py
questions_three/ci/junit2jenkins_status/__init__.py
questions_three/ci/junit2jenkins_status/__main__.py
questions_three/ci/junit2jenkins_status/junit2jenkins_status.py
questions_three/ci/junit2jenkins_status/status.py
questions_three/ci/run_all/__init__.py
questions_three/ci/run_all/__main__.py
questions_three/ci/run_all/get_search_path.py
questions_three/ci/run_all/job.py
questions_three/ci/run_all/pool.py
questions_three/ci/run_all/run_all.py
questions_three/constants/__init__.py
questions_three/constants/test_event.py
questions_three/constants/test_status.py
questions_three/event_broker/__init__.py
questions_three/event_broker/event_broker.py
questions_three/event_broker/handler_detection.py
questions_three/exceptions/__init__.py
questions_three/exceptions/http_error.py
questions_three/graphql/__init__.py
questions_three/graphql/graphql_client.py
questions_three/graphql/graphql_response.py
questions_three/graphql/operation_failed.py
questions_three/html_form/__init__.py
questions_three/html_form/exceptions.py
questions_three/html_form/html_form.py
questions_three/http_client/__init__.py
questions_three/http_client/construct_redirect_url.py
questions_three/http_client/extract_location_header.py
questions_three/http_client/http_client.py
questions_three/http_client/inspect_response.py
questions_three/http_client/transcript.py
questions_three/logging/__init__.py
questions_three/logging/constants.py
questions_three/logging/logger_for_module.py
questions_three/module_cfg/__init__.py
questions_three/module_cfg/loader.py
questions_three/module_cfg/module_cfg.py
questions_three/module_cfg/transform_type.py
questions_three/reporters/__init__.py
questions_three/reporters/artifact_saver/__init__.py
questions_three-3.14.2.0.dist-info/LICENSE
questions_three-3.14.2.0.dist-info/METADATA
questions_three-3.14.2.0.dist-info/WHEEL
questions_three-3.14.2.0.dist-info/top_level.txt
questions_three-3.14.2.0.dist-info/RECORD
