Metadata-Version: 2.1
Name: questions-three
Version: 3.14.2.0
Summary: Toolkit for building automated integration checks
Home-page: https://github.com/CyberGRX/questions-three
Author: Mike Duskis
Author-email: mike.duskis@cybergrx.com
License: UNKNOWN
Platform: UNKNOWN
Classifier: Development Status :: 5 - Production/Stable
Classifier: Intended Audience :: Developers
Classifier: License :: OSI Approved :: MIT License
Classifier: Natural Language :: English
Classifier: Operating System :: OS Independent
Classifier: Programming Language :: Python :: 3
Classifier: Topic :: Software Development :: Testing
Requires-Dist: expects (>=0.8.0)
Requires-Dist: junit-xml (==1.8)
Requires-Dist: lxml (>=4.1.1)
Requires-Dist: PyYAML (>=5.1)
Requires-Dist: pyfakefs (>=3.4.3)
Requires-Dist: requests (>=2.18.4)
Requires-Dist: twin-sister (>=4.2.6.0)
Requires-Dist: twine (>=1.9.1)
Requires-Dist: wheel (>=0.30.0)
Requires-Dist: parameterized (>=0.7.0)
